gplaycrawler/__init__.py
gplaycrawler/__main__.py
gplaycrawler/charts.py
gplaycrawler/main.py
gplaycrawler/metadata.py
gplaycrawler/packages.py
gplaycrawler/related.py
gplaycrawler/search.py
gplaycrawler/utils.py
gplaycrawler-0.2.1.dist-info/LICENSE.md
gplaycrawler-0.2.1.dist-info/METADATA
gplaycrawler-0.2.1.dist-info/WHEEL
gplaycrawler-0.2.1.dist-info/entry_points.txt
gplaycrawler-0.2.1.dist-info/top_level.txt
gplaycrawler-0.2.1.dist-info/RECORD
