Metadata-Version: 2.1
Name: gplaycrawler
Version: 0.2.1
Summary: Crawl the Google PlayStore
Home-page: https://gitlab.com/marzzzello/gplaycrawler
Author: marzzzello
Author-email: gplaycrawler@07f.de
License: UNKNOWN
Project-URL: Bug Tracker, https://gitlab.com/marzzzello/gplaycrawler/issues
Platform: UNKNOWN
Classifier: Programming Language :: Python :: 3
Classifier: License :: OSI Approved :: MIT License
Requires-Python: >=3.7
License-File: LICENSE.md
Requires-Dist: coloredlogs
Requires-Dist: reprint
Requires-Dist: playstoreapi
